cryptobacktest_yoen/__init__.py
cryptobacktest_yoen/cryptobacktest_yoen.py
cryptobacktest_yoen/option.py
cryptobacktest_yoen/straddlebacktest.py
cryptobacktest_yoen/straddlebroker.py
cryptobacktest_yoen/straddleinfo.py
cryptobacktest_yoen/volatility.py
cryptobacktest_yoen/volatilitysignal.py
cryptobacktest_yoen-0.0.1.dist-info/LICENSE
cryptobacktest_yoen-0.0.1.dist-info/METADATA
cryptobacktest_yoen-0.0.1.dist-info/WHEEL
cryptobacktest_yoen-0.0.1.dist-info/RECORD
