Metadata-Version: 2.3
Name: cryptobacktest_yoen
Version: 0.0.1
Summary: A package for backtesting crypocurrencies trading strategies
License: MIT
Author: Yoen Corbel
Author-email: Yoen.corbel-vivas@dauphine.eu
Requires-Python: >=3.12
Classifier: Programming Language :: Python :: 3
Classifier: Operating System :: OS Independent
Requires-Dist: matplotlib (>=3.10.0,<4.0.0)
Requires-Dist: norm (>=1.6.0,<2.0.0)
Requires-Dist: scipy (>=1.15.0,<2.0.0)
Project-URL: Homepage, https://github.com/YoenCorbel/cryptobacktest
Project-URL: Issues, https://github.com/YoenCorbel/cryptobacktest/issues
